nsense_face/__init__.py
nsense_face/face/__init__.py
nsense_face/face/common.py
nsense_face/model/__init__.py
nsense_face/model/load_arcface.py
nsense_face/model/load_onnx.py
nsense_face/model/load_trt.py
nsense_face/model/load_vino.py
nsense_face-0.0.13.dist-info/METADATA
nsense_face-0.0.13.dist-info/WHEEL
nsense_face-0.0.13.dist-info/top_level.txt
nsense_face-0.0.13.dist-info/RECORD
