Metadata-Version: 2.1
Name: nsense-face
Version: 0.0.13
Summary: nsense_face package
Author: minsuny
Author-email: minsun.y@nsensecorp.com
License: UNKNOWN
Platform: UNKNOWN
Requires-Python: >=3
Requires-Dist: numpy
Requires-Dist: onnxruntime
Requires-Dist: onnxruntime-gpu
Requires-Dist: torch
Requires-Dist: openvino (==2022.2.0)
